[{
    "codice":"1",
    "descrizione": {
		"it": "D. Lgs. 163/2006, art.57, c.2,lett.a). (N.B. per lavori<1.000.000 Euro)",
		"en": "D. Lgs. 163/2006, art.57, c.2,lett.a). (N.B. per lavori<1.000.000 Euro)"
		},
    "datainizio":null,
    "datafine":"2019-06-26T00:00:00Z"
},
{
    "codice":"2",
    "descrizione": {
		"it": "D. Lgs. 163/2006, art.57, c.2, lett.b).",
		"en": "D. Lgs. 163/2006, art.57, c.2, lett.b)."
		},
    "datainizio":null,
    "datafine":"2019-06-26T00:00:00Z"
},
{
    "codice":"3",
    "descrizione": {
		"it": "D. Lgs. 163/2006, art.57, c.2, lett.c).",
		"en": "D. Lgs. 163/2006, art.57, c.2, lett.c)."
		},	
    "datainizio":null,
    "datafine":"2019-06-26T00:00:00Z"
},
{
    "codice":"4",
    "descrizione": {
		"it": "D. Lgs. 163/2006, art.57, c.3, lett.a).(N.B. Solo per forniture)",
		"en": "D. Lgs. 163/2006, art.57, c.3, lett.a).(N.B. Solo per forniture)"
		},	
    "datainizio":null,
    "datafine":"2019-06-26T00:00:00Z"
},
{
    "codice":"5",
    "descrizione": {
		"it": "D. Lgs. 163/2006, art.57, c.3, lett.b).(N.B. Solo per forniture)",
		"en": "D. Lgs. 163/2006, art.57, c.3, lett.b).(N.B. Solo per forniture)"
		},	
    "datainizio":null,
    "datafine":"2019-06-26T00:00:00Z"
},
{
    "codice":"6",
    "descrizione": {
		"it": "D. Lgs. 163/2006, art.57, c.3, lett.c).(N.B. Solo per forniture)",
		"en": "D. Lgs. 163/2006, art.57, c.3, lett.c).(N.B. Solo per forniture)"
		},	
    "datainizio":null,
    "datafine":"2019-06-26T00:00:00Z"
},
{
    "codice":"7",
    "descrizione": {
		"it": "D. Lgs. 163/2006, art.57, c.3, lett.d).(N.B. Solo per forniture)",
		"en": "D. Lgs. 163/2006, art.57, c.3, lett.d).(N.B. Solo per forniture)"
		},		
    "datainizio":null,
    "datafine":"2019-06-26T00:00:00Z"
},
{
    "codice":"8",
    "descrizione": {
		"it": "D. Lgs. 163/2006, art.57, c.4.(N.B. Solo per Servizi)",
		"en": "D. Lgs. 163/2006, art.57, c.4.(N.B. Solo per Servizi)"
		},			    
    "datainizio":null,
    "datafine":"2019-06-26T00:00:00Z"
},
{
    "codice":"9",
    "descrizione": {
		"it": "D. Lgs. 163/2006, art.57, c.5, lett.a), sub a.1) (N.B. Solo per lavori e servizi)",
		"en": "D. Lgs. 163/2006, art.57, c.5, lett.a), sub a.1) (N.B. Solo per lavori e servizi)"
		},	
    "datainizio":null,
    "datafine":"2019-06-26T00:00:00Z"
},
{
    "codice":"10",
    "descrizione": {
		"it": "D. Lgs. 163/2006, art.57, c.5, lett.a), sub a.2) (N.B. Solo per lavori e servizi)",
		"en": "D. Lgs. 163/2006, art.57, c.5, lett.a), sub a.2) (N.B. Solo per lavori e servizi)"
		},	
    "datainizio":null,
    "datafine":"2019-06-26T00:00:00Z"
},
{
    "codice":"11",
    "descrizione": {
		"it": "D. Lgs. 163/2006, art.57, c.5, lett.b) (N.B. Solo per lavori e servizi)",
		"en": "D. Lgs. 163/2006, art.57, c.5, lett.b) (N.B. Solo per lavori e servizi)"
		},	
    "datainizio":null,
    "datafine":"2019-06-26T00:00:00Z"
},
{
    "codice":"12",
    "descrizione": {
		"it": "D.Lgs. 163/2006, art. 221, c. 1, lett. a) (N.B. Solo Settori Speciali)",
		"en": "D.Lgs. 163/2006, art. 221, c. 1, lett. a) (N.B. Solo Settori Speciali)"
		},	
    "datainizio":null,
    "datafine":"2019-06-26T00:00:00Z"
},
{
    "codice":"13",
    "descrizione": {
		"it": "D.Lgs. 163/2006, art. 221, c. 1, lett. b) (N.B. Solo Settori Speciali)",
		"en": "D.Lgs. 163/2006, art. 221, c. 1, lett. b) (N.B. Solo Settori Speciali)"
		},	
    "datainizio":null,
    "datafine":"2019-06-26T00:00:00Z"
},
{
    "codice":"14",
    "descrizione": {
		"it": "D.Lgs. 163/2006, art. 221, c. 1, lett. c) (N.B. Solo Settori Speciali)",
		"en": "D.Lgs. 163/2006, art. 221, c. 1, lett. c) (N.B. Solo Settori Speciali)"
		},
    "datainizio":null,
    "datafine":"2019-06-26T00:00:00Z"
},
{
    "codice":"15",
    "descrizione": {
		"it": "D.Lgs. 163/2006, art. 221, c. 1, lett. d) (N.B. Solo Settori Speciali)",
		"en": "D.Lgs. 163/2006, art. 221, c. 1, lett. d) (N.B. Solo Settori Speciali)"
		},
    "datainizio":null,
    "datafine":"2019-06-26T00:00:00Z"
},
{
    "codice":"16",
    "descrizione": {
		"it": "D.Lgs. 163/2006, art. 221, c. 1, lett. e) (N.B. Solo Settori Speciali)",
		"en": "D.Lgs. 163/2006, art. 221, c. 1, lett. e) (N.B. Solo Settori Speciali)"
		},
    "datainizio":null,
    "datafine":"2019-06-26T00:00:00Z"
},
{
    "codice":"17",
    "descrizione": {
		"it": "D.Lgs. 163/2006, art. 221, c. 1, lett. f) (N.B. Solo Settori Speciali)",
		"en": "D.Lgs. 163/2006, art. 221, c. 1, lett. f) (N.B. Solo Settori Speciali)"
		},
    "datainizio":null,
    "datafine":"2019-06-26T00:00:00Z"
},
{
    "codice":"18",
    "descrizione": {
		"it": "D.Lgs. 163/2006, art. 221, c. 1, lett. g) (N.B. Solo Settori Speciali)",
		"en": "D.Lgs. 163/2006, art. 221, c. 1, lett. g) (N.B. Solo Settori Speciali)"
		},
    "datainizio":null,
    "datafine":"2019-06-26T00:00:00Z"
},
{
    "codice":"19",
    "descrizione": {
		"it": "D.Lgs. 163/2006, art. 221, c. 1, lett. h) (N.B. Solo Settori Speciali)",
		"en": "D.Lgs. 163/2006, art. 221, c. 1, lett. h) (N.B. Solo Settori Speciali)"
		},
    "datainizio":null,
    "datafine":"2019-06-26T00:00:00Z"
},
{
    "codice":"20",
    "descrizione": {
		"it": "D.Lgs. 163/2006, art. 221, c. 1, lett. i) (N.B. Solo Settori Speciali)",
		"en": "D.Lgs. 163/2006, art. 221, c. 1, lett. i) (N.B. Solo Settori Speciali)"
		},
    "datainizio":null,
    "datafine":"2019-06-26T00:00:00Z"
},
{
    "codice":"21",
    "descrizione": {
		"it": "D.Lgs. 163/2006, art. 221, c. 1, lett. l) (N.B. Solo Settori Speciali)",
		"en": "D.Lgs. 163/2006, art. 221, c. 1, lett. l) (N.B. Solo Settori Speciali)"
		},
    "datainizio":null,
    "datafine":"2019-06-26T00:00:00Z"
},
{
    "codice":"22",
    "descrizione": {
		"it": "D.Lgs. 163/2006, art. 204, c. 1",
		"en": "D.Lgs. 163/2006, art. 204, c. 1"
		},
    "datainizio":null,
    "datafine":"2019-06-26T00:00:00Z"
},
{
    "codice":"23",
    "descrizione": {
		"it": "D.Lgs. 163/2006, art. 221, c. 1, lett. j) (N.B. Solo Settori Speciali)",
		"en": "D.Lgs. 163/2006, art. 221, c. 1, lett. j) (N.B. Solo Settori Speciali)"
		},
    "datainizio":null,
    "datafine":"2019-06-26T00:00:00Z"
},
{
    "codice":"24",
    "descrizione": {
		"it": "D.Lgs. 163/2006, art. 221, c. 1, lett. k) (N.B. Solo Settori Speciali)",
		"en": "D.Lgs. 163/2006, art. 221, c. 1, lett. k) (N.B. Solo Settori Speciali)"
		},
    "datainizio":null,
    "datafine":"2019-06-26T00:00:00Z"
},
{
    "codice":"25",
    "descrizione": {
		"it": "Altre motivazioni",
		"en": "Altre motivazioni"
		},
    "datainizio":null,
    "datafine":"2019-06-26T00:00:00Z"
},
{
    "codice":"26",
    "descrizione": {
		"it": "D. Lgs. 163/2006, art.122, c.7-bis (N.B. Solo per lavori)",
		"en": "D. Lgs. 163/2006, art.122, c.7-bis (N.B. Solo per lavori)"
		},
    "datainizio":null,
    "datafine":"2012-12-27T00:00:00Z"
},
{
    "codice":"27",
    "descrizione": {
		"it": "D. Lgs. 163/2006, art.122, c.8 (N.B. Solo per lavori)",
		"en": "D. Lgs. 163/2006, art.122, c.8 (N.B. Solo per lavori)"
		},
    "datainizio":null,
    "datafine":"2019-06-26T00:00:00Z"
},
{
    "codice":"28",
    "descrizione": {
		"it": "D. Lgs. 163/2006, art. 99, c.5 / art. 108 c.6",
		"en": "D. Lgs. 163/2006, art. 99, c.5 / art. 108 c.6"
		},
    "datainizio":null,
    "datafine":"2019-06-26T00:00:00Z"
},
{
    "codice":"29",
    "descrizione": {
		"it": "Ricorso al mercato elettronico",
		"en": "Ricorso al mercato elettronico"
		},
    "datainizio":null,
    "datafine":"2019-06-26T00:00:00Z"
},
{
    "codice":"30",
    "descrizione": {
		"it": "Adesione ad accordo quadro/convenzione",
		"en": "Adesione ad accordo quadro/convenzione"
		},
    "datainizio":null,
    "datafine":"2019-06-26T00:00:00Z"
},
{
    "codice":"31",
    "descrizione": {
		"it": "D. Lgs. 163/2006, art.122, c.7 (N.B. Solo per lavori)",
		"en": "D. Lgs. 163/2006, art.122, c.7 (N.B. Solo per lavori)"
		},
    "datainizio":null,
    "datafine":"2019-06-26T00:00:00Z"
},
{
    "codice":"32",
    "descrizione": {
		"it": "D. Lgs. 163/2006, art.91, c.2",
		"en": "D. Lgs. 163/2006, art.91, c.2"
		},
    "datainizio":null,
    "datafine":"2019-06-26T00:00:00Z"
},
{
    "codice":"33",
    "descrizione": {
		"it": "Procedura a seguito di precedente gara annullata o deserta o senza esito",
		"en": "Procedura a seguito di precedente gara annullata o deserta o senza esito"
		},
    "datainizio":null,
    "datafine":null
},
{
    "codice":"34",
    "descrizione": {
		"it": "Lavori, beni e servizi infungibili per opera d’arte",
		"en": "Lavori, beni e servizi infungibili per opera d’arte"
		},
    "datainizio":null,
    "datafine":null
},
{
    "codice":"35",
    "descrizione": {
		"it": "Lavori, beni e servizi infungibili per motivi tecnici",
		"en": "Lavori, beni e servizi infungibili per motivi tecnici"
		},
    "datainizio":null,
    "datafine":null
},
{
    "codice":"36",
    "descrizione": {
		"it": "Lavori, beni e servizi infungibili per diritti esclusivi",
		"en": "Lavori, beni e servizi infungibili per diritti esclusivi"
		},
    "datainizio":null,
    "datafine":null
},
{
    "codice":"37",
    "descrizione": {
		"it": "Estrema urgenza",
		"en": "Estrema urgenza"
		},
    "datainizio":null,
    "datafine":null
},
{
    "codice":"38",
    "descrizione": {
		"it": "Scopo di ricerca",
		"en": "Scopo di ricerca"
		},
    "datainizio":null,
    "datafine":null
},
{
    "codice":"39",
    "descrizione": {
		"it": "Consegne complementari",
		"en": "Consegne complementari"
		},
    "datainizio":null,
    "datafine":null
},
{
    "codice":"40",
    "descrizione": {
		"it": "Forniture quotate e acquistate sul mercato delle materie prime",
		"en": "Forniture quotate e acquistate sul mercato delle materie prime"
		},
    "datainizio":null,
    "datafine":null
},
{
    "codice":"41",
    "descrizione": {
		"it": "Condizioni particolarmente vantaggiose",
		"en": "Condizioni particolarmente vantaggiose"
		},
    "datainizio":null,
    "datafine":null
},
{
    "codice":"42",
    "descrizione": {
		"it": "Servizio di progettazione discendente da concorso di progettazione e idee",
		"en": "Servizio di progettazione discendente da concorso di progettazione e idee"
		},
    "datainizio":null,
    "datafine":null
},
{
    "codice":"43",
    "descrizione": {
		"it": "Ripetizione lavori o servizi analoghi",
		"en": "Ripetizione lavori o servizi analoghi"
		},
    "datainizio":null,
    "datafine":null
},
{
    "codice":"44",
    "descrizione": {
		"it": "Procedura di affidamento a contraente vincolato da disposizioni sovraordinate",
		"en": "Procedura di affidamento a contraente vincolato da disposizioni sovraordinate"
		},
    "datainizio":null,
    "datafine":null
},
{
    "codice":"45",
    "descrizione": {
		"it": "Procedura negoziata sottosoglia",
		"en": "Procedura negoziata sottosoglia"
		},
    "datainizio":null,
    "datafine":null
}]